fileSrch/__init__.py
fileSrch/filelist.py
fileSrch-0.0.2.dist-info/LICENSE
fileSrch-0.0.2.dist-info/METADATA
fileSrch-0.0.2.dist-info/WHEEL
fileSrch-0.0.2.dist-info/top_level.txt
fileSrch-0.0.2.dist-info/RECORD
