Metadata-Version: 2.1
Name: fileSrch
Version: 0.0.2
Summary: A simple package for searching files
Home-page: https://github.com/goutamenara/filemanager.git
Author: goutam
Author-email: goutam@protonmail.ch
License: UNKNOWN
Platform: UNKNOWN
Classifier: Programming Language :: Python :: 3
Classifier: License :: OSI Approved :: MIT License
Classifier: Operating System :: OS Independent
Requires-Python: >=3.6
